setup.py
fsb5/__init__.py
fsb5/pcm.py
fsb5/utils.py
fsb5/vorbis.py
fsb5/vorbis_headers.py
fsb5.egg-info/PKG-INFO
fsb5.egg-info/SOURCES.txt
fsb5.egg-info/dependency_links.txt
fsb5.egg-info/top_level.txt